desdeo_notebooks/__init__.py
desdeo_notebooks/__main__.py
desdeo_notebooks/nimbus-cylinder.ipynb
desdeo_notebooks/nimbus-river-pollution.ipynb
desdeo_notebooks/output/nimbus-cylinder.ipynb
desdeo_notebooks/output/nimbus-river-pollution.ipynb
desdeo_vis/__init__.py
desdeo_vis/_version.py
desdeo_vis/conf.py
desdeo_vis/nbextension/__init__.py
desdeo_vis/nbextension/static/extension.js
desdeo_vis/nbextension/static/index.js
desdeo_vis/nbextension/static/index.js.map
desdeo_vis/plot/__init__.py
desdeo_vis/plot/parallel.py
desdeo_vis/widget/__init__.py
desdeo_vis/widget/widgets.py
desdeo_vis-0.2.0.data/data/etc/jupyter/nbconfig/notebook.d/desdeo_vis.json
desdeo_vis-0.2.0.data/data/share/jupyter/nbextensions/desdeo_vis/extension.js
desdeo_vis-0.2.0.data/data/share/jupyter/nbextensions/desdeo_vis/index.js
desdeo_vis-0.2.0.data/data/share/jupyter/nbextensions/desdeo_vis/index.js.map
desdeo_vis-0.2.0.dist-info/METADATA
desdeo_vis-0.2.0.dist-info/RECORD
desdeo_vis-0.2.0.dist-info/WHEEL
desdeo_vis-0.2.0.dist-info/top_level.txt
