Metadata-Version: 2.1
Name: desdeo-vis
Version: 0.2.0
Summary: Visualisations and preference selection widgets for the DESDEO interactive multiobjective optimization library
Home-page: https://github.com/industrial-optimization-group/desdeo-vis
Author: Frankie Robertson
Author-email: frankie@robertson.name
License: MPL 2.0
Keywords: Jupyter,Widgets,IPython
Platform: Linux
Platform: Mac OS X
Platform: Windows
Classifier: Development Status :: 2 - Pre-Alpha
Classifier: Intended Audience :: Developers
Classifier: Intended Audience :: Science/Research
Classifier: License :: OSI Approved :: Mozilla Public License 2.0 (MPL 2.0)
Classifier: Programming Language :: Python
Classifier: Programming Language :: Python :: 3
Classifier: Programming Language :: Python :: 3.6
Classifier: Framework :: Jupyter
Provides-Extra: test
Provides-Extra: docs
Provides-Extra: dev
Requires-Dist: ipywidgets (>=7.0.0)
Requires-Dist: widgetsnbextension
Requires-Dist: desdeo (>=0.1.3)
Requires-Dist: matplotlib
Requires-Dist: altair
Requires-Dist: vega
Provides-Extra: dev
Requires-Dist: black (==18.4a4); extra == 'dev'
Requires-Dist: twine; extra == 'dev'
Requires-Dist: flake8; extra == 'dev'
Requires-Dist: isort; extra == 'dev'
Provides-Extra: docs
Requires-Dist: sphinx; extra == 'docs'
Requires-Dist: recommonmark; extra == 'docs'
Requires-Dist: sphinx-rtd-theme; extra == 'docs'
Requires-Dist: nbsphinx (>=0.2.13); extra == 'docs'
Requires-Dist: jupyter-sphinx; extra == 'docs'
Requires-Dist: nbsphinx-link; extra == 'docs'
Requires-Dist: pytest-check-links; extra == 'docs'
Requires-Dist: pypandoc; extra == 'docs'
Requires-Dist: sphinx-autodoc-typehints; extra == 'docs'
Provides-Extra: test
Requires-Dist: pytest; extra == 'test'
Requires-Dist: pytest-cov; extra == 'test'
Requires-Dist: nbval; extra == 'test'
